__init__.py
api_rester.py
lib/__init__.py
lib/api_runner.py
lib/config.py
lib/core.py
lib/data.py
lib/template.py
lib/util.py
api_rester-0.3.7.dist-info/LICENSE
api_rester-0.3.7.dist-info/METADATA
api_rester-0.3.7.dist-info/WHEEL
api_rester-0.3.7.dist-info/entry_points.txt
api_rester-0.3.7.dist-info/top_level.txt
api_rester-0.3.7.dist-info/RECORD
