Metadata-Version: 2.2
Name: api_rester
Version: 0.3.7
Summary: A simple REST API client CLI utility
Author-email: AlejandroJorge <a20202060@pucp.edu.pe>
License: MIT License
Project-URL: Homepage, https://github.com/AlejandroJorge/api-rester
Project-URL: Issues, https://github.com/AlejandroJorge/api-rester/issues
Classifier: Programming Language :: Python :: 3
Classifier: Operating System :: OS Independent
Requires-Python: >=3.8
License-File: LICENSE
Requires-Dist: requests>=2.32.3
Requires-Dist: pydantic>=2.10.6
Requires-Dist: dotenv>=0.9.9
